README.rst
setup.py
pyssh/__init__.py
pyssh/api.py
pyssh/compat.py
pyssh/exceptions.py
pyssh/forward.py
pyssh/result.py
pyssh/session.py
pyssh/sftp.py
pyssh/shell.py
pyssh_ctypes.egg-info/PKG-INFO
pyssh_ctypes.egg-info/SOURCES.txt
pyssh_ctypes.egg-info/dependency_links.txt
pyssh_ctypes.egg-info/requires.txt
pyssh_ctypes.egg-info/top_level.txt